pggraph/__init__.py
pggraph/api.py
pggraph/config.py
pggraph/main.py
pggraph/db/__init__.py
pggraph/db/archiver.py
pggraph/db/base.py
pggraph/db/build_references.py
pggraph/tests/__init__.py
pggraph/tests/test_api.py
pggraph/utils/__init__.py
pggraph/utils/action_enum.py
pggraph/utils/funcs.py
pggraph/utils/classes/__init__.py
pggraph/utils/classes/base.py
pggraph/utils/classes/foreign_key.py
pggraph-0.1.6.dist-info/LICENSE.md
pggraph-0.1.6.dist-info/METADATA
pggraph-0.1.6.dist-info/WHEEL
pggraph-0.1.6.dist-info/entry_points.txt
pggraph-0.1.6.dist-info/top_level.txt
pggraph-0.1.6.dist-info/RECORD
