Metadata-Version: 2.1
Name: pggraph
Version: 0.1.6
Summary: Утилита для работы с зависимостями таблиц в PostgreSQL
Home-page: https://github.com/domclick/pggraph
Author: "Sberbank Real Estate Center" Limited Liability Company <omborzov@domclick.ru> omborzov@domclick.ru
Author-email: omborzov@domclick.ru
License: MIT
Platform: UNKNOWN
Classifier: License :: OSI Approved :: MIT License
Classifier: Intended Audience :: Developers
Classifier: Operating System :: OS Independent
Classifier: Programming Language :: Python
Classifier: Programming Language :: Python :: 3
Classifier: Programming Language :: Python :: 3.6
Classifier: Programming Language :: Python :: 3.7
Classifier: Programming Language :: Python :: 3.8
Classifier: Topic :: Database
Classifier: Topic :: Utilities
Requires-Dist: psycopg2-binary (>=2.8)
Requires-Dist: dataclasses (>=0.5)
